smart_one_scripts/Process.py
smart_one_scripts/ProcessNotebooks.py
smart_one_scripts/__init__.py
smart_one_scripts/analysis_test.ipynb
smart_one_scripts-0.1.0.dist-info/WHEEL
smart_one_scripts-0.1.0.dist-info/METADATA
smart_one_scripts-0.1.0.dist-info/RECORD
