Metadata-Version: 2.1
Name: smart-one-scripts
Version: 0.1.0
Summary: 
License: MIT
Author: Breno Santos
Requires-Python: >=3.9
Classifier: License :: OSI Approved :: MIT License
Classifier: Programming Language :: Python :: 3
Classifier: Programming Language :: Python :: 3.10
Classifier: Programming Language :: Python :: 3.9
Requires-Dist: numpy (==1.25.1)
Requires-Dist: openpyxl (==3.1.2)
Requires-Dist: pandas (==2.0.0)
Requires-Dist: unidecode (==1.3.6)
